dashdot/__init__.py
dashdot-0.0.7.dist-info/METADATA
dashdot-0.0.7.dist-info/WHEEL
dashdot-0.0.7.dist-info/entry_points.txt
dashdot-0.0.7.dist-info/licenses/LICENSE
dashdot-0.0.7.dist-info/RECORD
