Metadata-Version: 2.3
Name: dashdot
Version: 0.0.7
Summary: A dotfiles manager to cure my sucky workflow
Project-URL: Homepage, https://github.com/try3d/dashdot
Project-URL: Bug Tracker, https://github.com/try3d/dashdot/issues
Author-email: Try3D <rsarans186@gmail.com>
License-File: LICENSE
Classifier: License :: OSI Approved :: MIT License
Classifier: Operating System :: OS Independent
Classifier: Programming Language :: Python :: 3
